{
    "bodyType": "required",
    "attrMax": 0,
    "parseBody": false,
    "status": "implemeted",
    "attrMin": 0,
    "hasNameAppendix": false,
    "name": "table",
    "type": "java",
    "attributeCollection": true,
    "attributeType": "fixed",
    "nameSpaceSeperator": "",
    "attributes": {
        "query": {
            "required": true,
            "status": "implemeted",
            "scriptSupport": "none",
            "type": "string",
            "description": "{{include:attribute_query.md}}"
        },
        "border": {
            "required": false,
            "status": "implemeted",
            "scriptSupport": "none",
            "type": "boolean",
            "description": "{{include:attribute_border.md}}"
        },
        "colspacing": {
            "required": false,
            "status": "implemeted",
            "scriptSupport": "none",
            "type": "number",
            "description": "{{include:attribute_colspacing.md}}"
        },
        "colheaders": {
            "required": false,
            "status": "implemeted",
            "scriptSupport": "none",
            "type": "boolean",
            "description": "{{include:attribute_colheaders.md}}"
        },
        "startrow": {
            "required": false,
            "status": "implemeted",
            "scriptSupport": "none",
            "type": "number",
            "description": "{{include:attribute_startrow.md}}"
        },
        "maxrows": {
            "required": false,
            "status": "implemeted",
            "scriptSupport": "none",
            "type": "number",
            "description": "{{include:attribute_maxrows.md}}"
        },
        "htmltable": {
            "required": false,
            "status": "implemeted",
            "scriptSupport": "none",
            "type": "boolean",
            "description": "{{include:attribute_htmltable.md}}"
        },
        "headerlines": {
            "required": false,
            "status": "implemeted",
            "scriptSupport": "none",
            "type": "number",
            "description": "{{include:attribute_headerlines.md}}"
        }
    },
    "description": "{{include:description.md}}",
    "nameSpace": "cf"
}