{
    "argMax": -1,
    "keywords": [
        "decision"
    ],
    "arguments": [
        {
            "required": true,
            "status": "implemeted",
            "name": "ip",
            "type": "String",
            "description": "{{include:argument_ip.md}}",
            "defaultValue": null
        }
    ],
    "argMin": 1,
    "returnType": "boolean",
    "status": "implemeted",
    "name": "islocalhost",
    "type": "java",
    "argumentType": "fixed",
    "description": "{{include:description.md}}"
}