{
    "bodyType": "prohibited",
    "attrMax": 0,
    "parseBody": false,
    "script": {
        "type": "multiple",
        "rtexpr": true
    },
    "status": "implemeted",
    "attrMin": 0,
    "hasNameAppendix": false,
    "name": "header",
    "type": "java",
    "attributeCollection": true,
    "attributeType": "fixed",
    "nameSpaceSeperator": "",
    "attributes": {
        "charset": {
            "required": false,
            "status": "implemeted",
            "scriptSupport": "none",
            "type": "string",
            "description": "{{include:attribute_charset.md}}"
        },
        "statustext": {
            "required": false,
            "status": "implemeted",
            "scriptSupport": "none",
            "type": "string",
            "description": "{{include:attribute_statustext.md}}"
        },
        "statuscode": {
            "required": false,
            "status": "implemeted",
            "scriptSupport": "none",
            "type": "number",
            "description": "{{include:attribute_statuscode.md}}"
        },
        "name": {
            "required": false,
            "status": "implemeted",
            "scriptSupport": "none",
            "type": "string",
            "description": "{{include:attribute_name.md}}"
        },
        "value": {
            "required": false,
            "status": "implemeted",
            "scriptSupport": "none",
            "type": "string",
            "description": "{{include:attribute_value.md}}"
        }
    },
    "description": "{{include:description.md}}",
    "nameSpace": "cf"
}