{
    "bodyType": "prohibited",
    "attrMax": 0,
    "parseBody": false,
    "status": "implemeted",
    "attrMin": 0,
    "hasNameAppendix": false,
    "name": "videoplayerparam",
    "type": "java",
    "attributeCollection": true,
    "attributeType": "fixed",
    "nameSpaceSeperator": "",
    "attributes": {
        "show": {
            "required": false,
            "status": "implemeted",
            "scriptSupport": "none",
            "type": "string",
            "description": "{{include:attribute_show.md}}"
        },
        "flash": {
            "required": false,
            "status": "implemeted",
            "scriptSupport": "none",
            "type": "string",
            "description": "{{include:attribute_flash.md}}"
        },
        "image": {
            "required": false,
            "status": "implemeted",
            "scriptSupport": "none",
            "type": "string",
            "description": "{{include:attribute_image.md}}"
        },
        "index": {
            "required": false,
            "status": "implemeted",
            "scriptSupport": "none",
            "type": "number",
            "description": "{{include:attribute_index.md}}"
        },
        "link": {
            "required": false,
            "status": "implemeted",
            "scriptSupport": "none",
            "type": "string",
            "description": "{{include:attribute_link.md}}"
        },
        "video": {
            "required": false,
            "status": "implemeted",
            "scriptSupport": "none",
            "type": "string",
            "description": "{{include:attribute_video.md}}"
        },
        "author": {
            "required": false,
            "status": "implemeted",
            "scriptSupport": "none",
            "type": "string",
            "description": "{{include:attribute_author.md}}"
        },
        "title": {
            "required": false,
            "status": "implemeted",
            "scriptSupport": "none",
            "type": "string",
            "description": "{{include:attribute_title.md}}"
        },
        "preview": {
            "required": false,
            "status": "implemeted",
            "scriptSupport": "none",
            "type": "string",
            "description": "{{include:attribute_preview.md}}"
        }
    },
    "description": "{{include:description.md}}",
    "nameSpace": "cf"
}