{
    "bodyType": "prohibited",
    "attrMax": 0,
    "parseBody": false,
    "script": {
        "type": "multiple",
        "rtexpr": true
    },
    "status": "implemeted",
    "attrMin": 0,
    "hasNameAppendix": false,
    "name": "param",
    "type": "java",
    "attributeCollection": false,
    "attributeType": "mixed",
    "nameSpaceSeperator": "",
    "attributes": {
        "default": {
            "required": false,
            "status": "implemeted",
            "scriptSupport": "none",
            "type": "any",
            "description": "{{include:attribute_default.md}}"
        },
        "pattern": {
            "required": false,
            "status": "implemeted",
            "scriptSupport": "none",
            "type": "string",
            "description": "{{include:attribute_pattern.md}}"
        },
        "maxlength": {
            "required": false,
            "status": "implemeted",
            "scriptSupport": "none",
            "type": "int",
            "description": "{{include:attribute_maxlength.md}}"
        },
        "min": {
            "required": false,
            "status": "implemeted",
            "scriptSupport": "none",
            "type": "number",
            "description": "{{include:attribute_min.md}}"
        },
        "name": {
            "required": true,
            "status": "implemeted",
            "scriptSupport": "none",
            "type": "string",
            "description": "{{include:attribute_name.md}}"
        },
        "type": {
            "required": false,
            "status": "implemeted",
            "scriptSupport": "none",
            "type": "string",
            "description": "{{include:attribute_type.md}}"
        },
        "max": {
            "required": false,
            "status": "implemeted",
            "scriptSupport": "none",
            "type": "number",
            "description": "{{include:attribute_max.md}}"
        }
    },
    "description": "{{include:description.md}}",
    "nameSpace": "cf"
}